LICENSE
MANIFEST.in
README.rst
setup.py
bee_django_coin/__init__.py
bee_django_coin/admin.py
bee_django_coin/apps.py
bee_django_coin/decorators.py
bee_django_coin/exports.py
bee_django_coin/forms.py
bee_django_coin/models.py
bee_django_coin/signals.py
bee_django_coin/tests.py
bee_django_coin/urls.py
bee_django_coin/utils.py
bee_django_coin/views.py
bee_django_coin.egg-info/PKG-INFO
bee_django_coin.egg-info/SOURCES.txt
bee_django_coin.egg-info/dependency_links.txt
bee_django_coin.egg-info/requires.txt
bee_django_coin.egg-info/top_level.txt
bee_django_coin/migrations/0001_initial.py
bee_django_coin/migrations/0001_initial.pyc
bee_django_coin/migrations/0002_cointype_identity.py
bee_django_coin/migrations/0002_cointype_identity.pyc
bee_django_coin/migrations/0003_usercoincount.py
bee_django_coin/migrations/0003_usercoincount.pyc
bee_django_coin/migrations/0004_auto_20180620_1845.py
bee_django_coin/migrations/0004_auto_20180620_1845.pyc
bee_django_coin/migrations/0005_auto_20181016_1619.py
bee_django_coin/migrations/0005_auto_20181016_1619.pyc
bee_django_coin/migrations/0006_auto_20181016_1717.py
bee_django_coin/migrations/0006_auto_20181016_1717.pyc
bee_django_coin/migrations/0007_auto_20181018_1508.py
bee_django_coin/migrations/0007_auto_20181018_1508.pyc
bee_django_coin/migrations/0008_auto_20181019_1557.py
bee_django_coin/migrations/0008_auto_20181019_1557.pyc
bee_django_coin/migrations/0009_item_order.py
bee_django_coin/migrations/0009_item_order.pyc
bee_django_coin/migrations/0010_auto_20181109_1415.py
bee_django_coin/migrations/0010_auto_20181109_1415.pyc
bee_django_coin/migrations/0011_auto_20181109_1422.py
bee_django_coin/migrations/0011_auto_20181109_1422.pyc
bee_django_coin/migrations/0012_auto_20181112_1527.py
bee_django_coin/migrations/0012_auto_20181112_1527.pyc
bee_django_coin/migrations/0013_auto_20181112_1534.py
bee_django_coin/migrations/0013_auto_20181112_1534.pyc
bee_django_coin/migrations/0014_item_url.py
bee_django_coin/migrations/0014_item_url.pyc
bee_django_coin/migrations/0015_auto_20181122_1337.py
bee_django_coin/migrations/0015_auto_20181122_1337.pyc
bee_django_coin/migrations/0016_auto_20181219_2057.py
